[
 {
  "type": "template",
  "altText": "this is a carousel template",
  "template": {
    "type": "carousel",
    "actions": [],
    "columns": [
      {
        "title": "Mega Stone",
        "text": "抱石場",
        "actions": [
          {
            "type": "postback",
            "label": "價目表",
            "data": "folder=North_MegaStone價目表"
          },
          {
            "type": "postback",
            "label": "地址",
            "data": "folder=North_MegaStone地址"
          },
          {
            "type": "postback",
            "label": "電話",
            "data": "folder=North_MegaStone電話"
          }
        ]
      }
    ]
  }
}]